<annotation verified="yes">
  <folder>Annotation</folder>
  <filename>v_g085_002881.jpg</filename>
  <path>PitchAndUmpireTesting-PascalVOC-export/Annotations/v_g085_002881.jpg</path>
  <source>
    <database>Unknown</database>
  </source>
  <size>
    <width>1920</width>
    <height>1080</height>
    <depth>3</depth>
  </size>
  <segmented>0</segmented>
  <object>
    <name>Umpire</name>
    <pose>Unspecified</pose>
    <truncated>0</truncated>
    <difficult>0</difficult>
    <bndbox>
      <xmin>786.6408</xmin>
      <ymin>639.728118</ymin>
      <xmax>1012.1941439999999</xmax>
      <ymax>1077.786378</ymax>
    </bndbox>
  </object>
  <object>
    <name>Pitch</name>
    <pose>Unspecified</pose>
    <truncated>0</truncated>
    <difficult>0</difficult>
    <bndbox>
      <xmin>482.79619199999996</xmin>
      <ymin>395.53396200000003</ymin>
      <xmax>1252.66032</xmax>
      <ymax>1077.78627</ymax>
    </bndbox>
  </object>
</annotation>