<annotation verified="yes">
  <folder>Annotation</folder>
  <filename>v_g072_055390.jpg</filename>
  <path>PitchAndUmpireTesting-PascalVOC-export/Annotations/v_g072_055390.jpg</path>
  <source>
    <database>Unknown</database>
  </source>
  <size>
    <width>1920</width>
    <height>1080</height>
    <depth>3</depth>
  </size>
  <segmented>0</segmented>
  <object>
    <name>Umpire</name>
    <pose>Unspecified</pose>
    <truncated>0</truncated>
    <difficult>0</difficult>
    <bndbox>
      <xmin>777.674496</xmin>
      <ymin>829.302408</ymin>
      <xmax>1101.395328</xmax>
      <ymax>1080</ymax>
    </bndbox>
  </object>
  <object>
    <name>Pitch</name>
    <pose>Unspecified</pose>
    <truncated>0</truncated>
    <difficult>0</difficult>
    <bndbox>
      <xmin>439.0697279999999</xmin>
      <ymin>604.18602</ymin>
      <xmax>1413.953376</xmax>
      <ymax>1079.999892</ymax>
    </bndbox>
  </object>
</annotation>