<annotation verified="yes">
  <folder>Annotation</folder>
  <filename>v_g092_002216.jpg</filename>
  <path>PitchAndUmpireTesting-PascalVOC-export/Annotations/v_g092_002216.jpg</path>
  <source>
    <database>Unknown</database>
  </source>
  <size>
    <width>1920</width>
    <height>1080</height>
    <depth>3</depth>
  </size>
  <segmented>0</segmented>
  <object>
    <name>Umpire</name>
    <pose>Unspecified</pose>
    <truncated>0</truncated>
    <difficult>0</difficult>
    <bndbox>
      <xmin>794.0970623999999</xmin>
      <ymin>499.9222800000001</ymin>
      <xmax>945.0873216</xmax>
      <ymax>923.0680080000001</ymax>
    </bndbox>
  </object>
  <object>
    <name>Pitch</name>
    <pose>Unspecified</pose>
    <truncated>0</truncated>
    <difficult>0</difficult>
    <bndbox>
      <xmin>548.038848</xmin>
      <ymin>320.97087000000005</ymin>
      <xmax>1179.9611519999999</xmax>
      <ymax>889.514514</ymax>
    </bndbox>
  </object>
</annotation>