<annotation verified="yes">
  <folder>Annotation</folder>
  <filename>v_g072_050334.jpg</filename>
  <path>PitchAndUmpireTesting-PascalVOC-export/Annotations/v_g072_050334.jpg</path>
  <source>
    <database>Unknown</database>
  </source>
  <size>
    <width>1920</width>
    <height>1080</height>
    <depth>3</depth>
  </size>
  <segmented>0</segmented>
  <object>
    <name>Umpire</name>
    <pose>Unspecified</pose>
    <truncated>0</truncated>
    <difficult>0</difficult>
    <bndbox>
      <xmin>879.9999071999999</xmin>
      <ymin>434.88370799999996</ymin>
      <xmax>1021.3952928</xmax>
      <ymax>842.325588</ymax>
    </bndbox>
  </object>
  <object>
    <name>Pitch</name>
    <pose>Unspecified</pose>
    <truncated>0</truncated>
    <difficult>0</difficult>
    <bndbox>
      <xmin>673.488384</xmin>
      <ymin>312.093</ymin>
      <xmax>1244.651136</xmax>
      <ymax>788.372136</ymax>
    </bndbox>
  </object>
</annotation>