<annotation verified="yes">
  <folder>Annotation</folder>
  <filename>v_g079_042786.jpg</filename>
  <path>PitchAndUmpireTesting-PascalVOC-export/Annotations/v_g079_042786.jpg</path>
  <source>
    <database>Unknown</database>
  </source>
  <size>
    <width>1920</width>
    <height>1080</height>
    <depth>3</depth>
  </size>
  <segmented>0</segmented>
  <object>
    <name>Umpire</name>
    <pose>Unspecified</pose>
    <truncated>0</truncated>
    <difficult>0</difficult>
    <bndbox>
      <xmin>839.0698176000001</xmin>
      <ymin>486.97675200000003</ymin>
      <xmax>989.7674304</xmax>
      <ymax>881.395344</ymax>
    </bndbox>
  </object>
  <object>
    <name>Pitch</name>
    <pose>Unspecified</pose>
    <truncated>0</truncated>
    <difficult>0</difficult>
    <bndbox>
      <xmin>647.4419519999999</xmin>
      <ymin>304.65120600000006</ymin>
      <xmax>1200.000096</xmax>
      <ymax>808.8372180000001</ymax>
    </bndbox>
  </object>
</annotation>