<annotation verified="yes">
  <folder>Annotation</folder>
  <filename>v_g069_036621.jpg</filename>
  <path>PitchAndUmpireTesting-PascalVOC-export/Annotations/v_g069_036621.jpg</path>
  <source>
    <database>Unknown</database>
  </source>
  <size>
    <width>1920</width>
    <height>1080</height>
    <depth>3</depth>
  </size>
  <segmented>0</segmented>
  <object>
    <name>Umpire</name>
    <pose>Unspecified</pose>
    <truncated>0</truncated>
    <difficult>0</difficult>
    <bndbox>
      <xmin>868.8372864</xmin>
      <ymin>548.3720519999999</ymin>
      <xmax>1012.0930176000002</xmax>
      <ymax>905.581404</ymax>
    </bndbox>
  </object>
  <object>
    <name>Pitch</name>
    <pose>Unspecified</pose>
    <truncated>0</truncated>
    <difficult>0</difficult>
    <bndbox>
      <xmin>697.6745280000001</xmin>
      <ymin>379.0697939999999</ymin>
      <xmax>1190.6976960000002</xmax>
      <ymax>838.6047179999999</ymax>
    </bndbox>
  </object>
</annotation>