<annotation verified="yes">
  <folder>Annotation</folder>
  <filename>v_g088_047198.jpg</filename>
  <path>PitchAndUmpireTesting-PascalVOC-export/Annotations/v_g088_047198.jpg</path>
  <source>
    <database>Unknown</database>
  </source>
  <size>
    <width>1920</width>
    <height>1080</height>
    <depth>3</depth>
  </size>
  <segmented>0</segmented>
  <object>
    <name>Umpire</name>
    <pose>Unspecified</pose>
    <truncated>0</truncated>
    <difficult>0</difficult>
    <bndbox>
      <xmin>883.5728352</xmin>
      <ymin>496.1941199999999</ymin>
      <xmax>1030.8349728</xmax>
      <ymax>870.8737679999999</ymax>
    </bndbox>
  </object>
  <object>
    <name>Pitch</name>
    <pose>Unspecified</pose>
    <truncated>0</truncated>
    <difficult>0</difficult>
    <bndbox>
      <xmin>689.708736</xmin>
      <ymin>334.01943</ymin>
      <xmax>1217.24256</xmax>
      <ymax>826.1360099999999</ymax>
    </bndbox>
  </object>
</annotation>