<annotation verified="yes">
  <folder>Annotation</folder>
  <filename>v_g022_025980.jpg</filename>
  <path>PitchAndUmpireTesting-PascalVOC-export/Annotations/v_g022_025980.jpg</path>
  <source>
    <database>Unknown</database>
  </source>
  <size>
    <width>1920</width>
    <height>1080</height>
    <depth>3</depth>
  </size>
  <segmented>0</segmented>
  <object>
    <name>Umpire</name>
    <pose>Unspecified</pose>
    <truncated>0</truncated>
    <difficult>0</difficult>
    <bndbox>
      <xmin>909.7673472</xmin>
      <ymin>494.4186</ymin>
      <xmax>1036.2789888</xmax>
      <ymax>853.4883600000001</ymax>
    </bndbox>
  </object>
  <object>
    <name>Pitch</name>
    <pose>Unspecified</pose>
    <truncated>0</truncated>
    <difficult>0</difficult>
    <bndbox>
      <xmin>710.6976</xmin>
      <ymin>420.00006600000006</ymin>
      <xmax>1233.488256</xmax>
      <ymax>812.5581420000001</ymax>
    </bndbox>
  </object>
</annotation>