<annotation verified="yes">
  <folder>Annotation</folder>
  <filename>v_g014_046776.jpg</filename>
  <path>PitchAndUmpireTesting-PascalVOC-export/Annotations/v_g014_046776.jpg</path>
  <source>
    <database>Unknown</database>
  </source>
  <size>
    <width>1920</width>
    <height>1080</height>
    <depth>3</depth>
  </size>
  <segmented>0</segmented>
  <object>
    <name>Umpire</name>
    <pose>Unspecified</pose>
    <truncated>0</truncated>
    <difficult>0</difficult>
    <bndbox>
      <xmin>902.3256191999999</xmin>
      <ymin>568.837188</ymin>
      <xmax>1045.5815808</xmax>
      <ymax>944.6510519999999</ymax>
    </bndbox>
  </object>
  <object>
    <name>Pitch</name>
    <pose>Unspecified</pose>
    <truncated>0</truncated>
    <difficult>0</difficult>
    <bndbox>
      <xmin>705.1161600000001</xmin>
      <ymin>230.23251</ymin>
      <xmax>1244.651136</xmax>
      <ymax>881.3952899999999</ymax>
    </bndbox>
  </object>
</annotation>