<annotation verified="yes">
  <folder>Annotation</folder>
  <filename>v_g013_044023.jpg</filename>
  <path>PitchAndUmpireTesting-PascalVOC-export/Annotations/v_g013_044023.jpg</path>
  <source>
    <database>Unknown</database>
  </source>
  <size>
    <width>1920</width>
    <height>1080</height>
    <depth>3</depth>
  </size>
  <segmented>0</segmented>
  <object>
    <name>Umpire</name>
    <pose>Unspecified</pose>
    <truncated>0</truncated>
    <difficult>0</difficult>
    <bndbox>
      <xmin>941.3952864</xmin>
      <ymin>637.674336</ymin>
      <xmax>1060.4650656000001</xmax>
      <ymax>926.0464320000001</ymax>
    </bndbox>
  </object>
  <object>
    <name>Pitch</name>
    <pose>Unspecified</pose>
    <truncated>0</truncated>
    <difficult>0</difficult>
    <bndbox>
      <xmin>811.1627520000002</xmin>
      <ymin>401.39528399999995</ymin>
      <xmax>1194.41856</xmax>
      <ymax>836.744148</ymax>
    </bndbox>
  </object>
</annotation>