<annotation verified="yes">
  <folder>Annotation</folder>
  <filename>v_g028_053701.jpg</filename>
  <path>PitchAndUmpireTesting-PascalVOC-export/Annotations/v_g028_053701.jpg</path>
  <source>
    <database>Unknown</database>
  </source>
  <size>
    <width>1920</width>
    <height>1080</height>
    <depth>3</depth>
  </size>
  <segmented>0</segmented>
  <object>
    <name>Umpire</name>
    <pose>Unspecified</pose>
    <truncated>0</truncated>
    <difficult>0</difficult>
    <bndbox>
      <xmin>919.069728</xmin>
      <ymin>442.32555600000006</ymin>
      <xmax>1039.999968</xmax>
      <ymax>769.7675160000001</ymax>
    </bndbox>
  </object>
  <object>
    <name>Pitch</name>
    <pose>Unspecified</pose>
    <truncated>0</truncated>
    <difficult>0</difficult>
    <bndbox>
      <xmin>760.930368</xmin>
      <ymin>364.186152</ymin>
      <xmax>1216.744128</xmax>
      <ymax>740.000016</ymax>
    </bndbox>
  </object>
</annotation>