<annotation verified="yes">
  <folder>Annotation</folder>
  <filename>v_g078_014939.jpg</filename>
  <path>PitchAndUmpireTesting-PascalVOC-export/Annotations/v_g078_014939.jpg</path>
  <source>
    <database>Unknown</database>
  </source>
  <size>
    <width>1920</width>
    <height>1080</height>
    <depth>3</depth>
  </size>
  <segmented>0</segmented>
  <object>
    <name>Umpire</name>
    <pose>Unspecified</pose>
    <truncated>0</truncated>
    <difficult>0</difficult>
    <bndbox>
      <xmin>868.8372384</xmin>
      <ymin>466.51166999999987</ymin>
      <xmax>1015.8140256</xmax>
      <ymax>831.1627619999999</ymax>
    </bndbox>
  </object>
  <object>
    <name>Pitch</name>
    <pose>Unspecified</pose>
    <truncated>0</truncated>
    <difficult>0</difficult>
    <bndbox>
      <xmin>686.511552</xmin>
      <ymin>299.06981999999994</ymin>
      <xmax>1220.465088</xmax>
      <ymax>758.604636</ymax>
    </bndbox>
  </object>
</annotation>