<annotation verified="yes">
  <folder>Annotation</folder>
  <filename>v_g096_016892.jpg</filename>
  <path>PitchAndUmpireTesting-PascalVOC-export/Annotations/v_g096_016892.jpg</path>
  <source>
    <database>Unknown</database>
  </source>
  <size>
    <width>1920</width>
    <height>1080</height>
    <depth>3</depth>
  </size>
  <segmented>0</segmented>
  <object>
    <name>Umpire</name>
    <pose>Unspecified</pose>
    <truncated>0</truncated>
    <difficult>0</difficult>
    <bndbox>
      <xmin>896.6213088</xmin>
      <ymin>565.16508</ymin>
      <xmax>1040.1552672</xmax>
      <ymax>898.8349679999999</ymax>
    </bndbox>
  </object>
  <object>
    <name>Pitch</name>
    <pose>Unspecified</pose>
    <truncated>0</truncated>
    <difficult>0</difficult>
    <bndbox>
      <xmin>706.485408</xmin>
      <ymin>270.640764</ymin>
      <xmax>1224.6989760000001</xmax>
      <ymax>839.184516</ymax>
    </bndbox>
  </object>
</annotation>