<annotation verified="yes">
  <folder>Annotation</folder>
  <filename>v_g076_019801.jpg</filename>
  <path>PitchAndUmpireTesting-PascalVOC-export/Annotations/v_g076_019801.jpg</path>
  <source>
    <database>Unknown</database>
  </source>
  <size>
    <width>1920</width>
    <height>1080</height>
    <depth>3</depth>
  </size>
  <segmented>0</segmented>
  <object>
    <name>Umpire</name>
    <pose>Unspecified</pose>
    <truncated>0</truncated>
    <difficult>0</difficult>
    <bndbox>
      <xmin>883.7208864</xmin>
      <ymin>447.90694199999996</ymin>
      <xmax>1030.6976736000001</xmax>
      <ymax>766.0465379999999</ymax>
    </bndbox>
  </object>
  <object>
    <name>Pitch</name>
    <pose>Unspecified</pose>
    <truncated>0</truncated>
    <difficult>0</difficult>
    <bndbox>
      <xmin>708.83712</xmin>
      <ymin>347.441832</ymin>
      <xmax>1194.41856</xmax>
      <ymax>721.3952879999999</ymax>
    </bndbox>
  </object>
</annotation>