<annotation verified="yes">
  <folder>Annotation</folder>
  <filename>v_g003_002221.jpg</filename>
  <path>PitchAndUmpireTesting-PascalVOC-export/Annotations/v_g003_002221.jpg</path>
  <source>
    <database>Unknown</database>
  </source>
  <size>
    <width>1920</width>
    <height>1080</height>
    <depth>3</depth>
  </size>
  <segmented>0</segmented>
  <object>
    <name>Umpire</name>
    <pose>Unspecified</pose>
    <truncated>0</truncated>
    <difficult>0</difficult>
    <bndbox>
      <xmin>904.1861088</xmin>
      <ymin>499.99998600000004</ymin>
      <xmax>1034.4186912</xmax>
      <ymax>827.441838</ymax>
    </bndbox>
  </object>
  <object>
    <name>Pitch</name>
    <pose>Unspecified</pose>
    <truncated>0</truncated>
    <difficult>0</difficult>
    <bndbox>
      <xmin>736.74432</xmin>
      <ymin>334.41865199999995</ymin>
      <xmax>1198.13952</xmax>
      <ymax>769.767516</ymax>
    </bndbox>
  </object>
</annotation>