<annotation verified="yes">
  <folder>Annotation</folder>
  <filename>v_g033_030216.jpg</filename>
  <path>PitchAndUmpireTesting-PascalVOC-export/Annotations/v_g033_030216.jpg</path>
  <source>
    <database>Unknown</database>
  </source>
  <size>
    <width>1920</width>
    <height>1080</height>
    <depth>3</depth>
  </size>
  <segmented>0</segmented>
  <object>
    <name>Umpire</name>
    <pose>Unspecified</pose>
    <truncated>0</truncated>
    <difficult>0</difficult>
    <bndbox>
      <xmin>902.3256288</xmin>
      <ymin>516.7441980000001</ymin>
      <xmax>1034.4186912</xmax>
      <ymax>870.232626</ymax>
    </bndbox>
  </object>
  <object>
    <name>Pitch</name>
    <pose>Unspecified</pose>
    <truncated>0</truncated>
    <difficult>0</difficult>
    <bndbox>
      <xmin>731.16288</xmin>
      <ymin>436.744116</ymin>
      <xmax>1200</xmax>
      <ymax>786.51162</ymax>
    </bndbox>
  </object>
</annotation>