<annotation verified="yes">
  <folder>Annotation</folder>
  <filename>v_g032_027198.jpg</filename>
  <path>PitchAndUmpireTesting-PascalVOC-export/Annotations/v_g032_027198.jpg</path>
  <source>
    <database>Unknown</database>
  </source>
  <size>
    <width>1920</width>
    <height>1080</height>
    <depth>3</depth>
  </size>
  <segmented>0</segmented>
  <object>
    <name>Umpire</name>
    <pose>Unspecified</pose>
    <truncated>0</truncated>
    <difficult>0</difficult>
    <bndbox>
      <xmin>911.6279328</xmin>
      <ymin>607.907052</ymin>
      <xmax>1017.6744672</xmax>
      <ymax>834.88374</ymax>
    </bndbox>
  </object>
  <object>
    <name>Pitch</name>
    <pose>Unspecified</pose>
    <truncated>0</truncated>
    <difficult>0</difficult>
    <bndbox>
      <xmin>809.3022719999999</xmin>
      <ymin>416.2791419999999</ymin>
      <xmax>1116.279168</xmax>
      <ymax>801.39537</ymax>
    </bndbox>
  </object>
</annotation>