<annotation verified="yes">
  <folder>Annotation</folder>
  <filename>v_g031_041192.jpg</filename>
  <path>PitchAndUmpireTesting-PascalVOC-export/Annotations/v_g031_041192.jpg</path>
  <source>
    <database>Unknown</database>
  </source>
  <size>
    <width>1920</width>
    <height>1080</height>
    <depth>3</depth>
  </size>
  <segmented>0</segmented>
  <object>
    <name>Umpire</name>
    <pose>Unspecified</pose>
    <truncated>0</truncated>
    <difficult>0</difficult>
    <bndbox>
      <xmin>926.5116672000001</xmin>
      <ymin>481.395258</ymin>
      <xmax>1101.3954048</xmax>
      <ymax>924.185862</ymax>
    </bndbox>
  </object>
  <object>
    <name>Pitch</name>
    <pose>Unspecified</pose>
    <truncated>0</truncated>
    <difficult>0</difficult>
    <bndbox>
      <xmin>684.6510719999999</xmin>
      <ymin>312.093</ymin>
      <xmax>1352.558016</xmax>
      <ymax>859.0698</ymax>
    </bndbox>
  </object>
</annotation>