<annotation verified="yes">
  <folder>Annotation</folder>
  <filename>v_g029_025293.jpg</filename>
  <path>PitchAndUmpireTesting-PascalVOC-export/Annotations/v_g029_025293.jpg</path>
  <source>
    <database>Unknown</database>
  </source>
  <size>
    <width>1920</width>
    <height>1080</height>
    <depth>3</depth>
  </size>
  <segmented>0</segmented>
  <object>
    <name>Umpire</name>
    <pose>Unspecified</pose>
    <truncated>0</truncated>
    <difficult>0</difficult>
    <bndbox>
      <xmin>814.883712</xmin>
      <ymin>503.72091</ymin>
      <xmax>961.8604799999999</xmax>
      <ymax>892.55817</ymax>
    </bndbox>
  </object>
  <object>
    <name>Pitch</name>
    <pose>Unspecified</pose>
    <truncated>0</truncated>
    <difficult>0</difficult>
    <bndbox>
      <xmin>612.092928</xmin>
      <ymin>276.7442220000001</ymin>
      <xmax>1198.13952</xmax>
      <ymax>808.8372180000001</ymax>
    </bndbox>
  </object>
</annotation>