<annotation verified="yes">
  <folder>Annotation</folder>
  <filename>v_g052_018041.jpg</filename>
  <path>PitchAndUmpireTesting-PascalVOC-export/Annotations/v_g052_018041.jpg</path>
  <source>
    <database>Unknown</database>
  </source>
  <size>
    <width>1920</width>
    <height>1080</height>
    <depth>3</depth>
  </size>
  <segmented>0</segmented>
  <object>
    <name>Umpire</name>
    <pose>Unspecified</pose>
    <truncated>0</truncated>
    <difficult>0</difficult>
    <bndbox>
      <xmin>904.18608</xmin>
      <ymin>507.441834</ymin>
      <xmax>1026.9768</xmax>
      <ymax>827.441838</ymax>
    </bndbox>
  </object>
  <object>
    <name>Pitch</name>
    <pose>Unspecified</pose>
    <truncated>0</truncated>
    <difficult>0</difficult>
    <bndbox>
      <xmin>742.325664</xmin>
      <ymin>379.06974</ymin>
      <xmax>1200.000096</xmax>
      <ymax>773.488332</ymax>
    </bndbox>
  </object>
</annotation>