<annotation verified="yes">
  <folder>Annotation</folder>
  <filename>v_g026_049779.jpg</filename>
  <path>PitchAndUmpireTesting-PascalVOC-export/Annotations/v_g026_049779.jpg</path>
  <source>
    <database>Unknown</database>
  </source>
  <size>
    <width>1920</width>
    <height>1080</height>
    <depth>3</depth>
  </size>
  <segmented>0</segmented>
  <object>
    <name>Umpire</name>
    <pose>Unspecified</pose>
    <truncated>0</truncated>
    <difficult>0</difficult>
    <bndbox>
      <xmin>861.3953088</xmin>
      <ymin>514.883736</ymin>
      <xmax>993.4882752</xmax>
      <ymax>857.209392</ymax>
    </bndbox>
  </object>
  <object>
    <name>Pitch</name>
    <pose>Unspecified</pose>
    <truncated>0</truncated>
    <difficult>0</difficult>
    <bndbox>
      <xmin>684.651072</xmin>
      <ymin>340.000038</ymin>
      <xmax>1162.790592</xmax>
      <ymax>806.97681</ymax>
    </bndbox>
  </object>
</annotation>