<annotation verified="yes">
  <folder>Annotation</folder>
  <filename>v_g052_034142.jpg</filename>
  <path>PitchAndUmpireTesting-PascalVOC-export/Annotations/v_g052_034142.jpg</path>
  <source>
    <database>Unknown</database>
  </source>
  <size>
    <width>1920</width>
    <height>1080</height>
    <depth>3</depth>
  </size>
  <segmented>0</segmented>
  <object>
    <name>Umpire</name>
    <pose>Unspecified</pose>
    <truncated>0</truncated>
    <difficult>0</difficult>
    <bndbox>
      <xmin>894.8836319999999</xmin>
      <ymin>438.604686</ymin>
      <xmax>1006.511568</xmax>
      <ymax>749.3024340000001</ymax>
    </bndbox>
  </object>
  <object>
    <name>Pitch</name>
    <pose>Unspecified</pose>
    <truncated>0</truncated>
    <difficult>0</difficult>
    <bndbox>
      <xmin>736.744128</xmin>
      <ymin>338.13952199999994</ymin>
      <xmax>1164.6510719999999</xmax>
      <ymax>689.767542</ymax>
    </bndbox>
  </object>
</annotation>