<annotation verified="yes">
  <folder>Annotation</folder>
  <filename>v_g034_021939.jpg</filename>
  <path>PitchAndUmpireTesting-PascalVOC-export/Annotations/v_g034_021939.jpg</path>
  <source>
    <database>Unknown</database>
  </source>
  <size>
    <width>1920</width>
    <height>1080</height>
    <depth>3</depth>
  </size>
  <segmented>0</segmented>
  <object>
    <name>Umpire</name>
    <pose>Unspecified</pose>
    <truncated>0</truncated>
    <difficult>0</difficult>
    <bndbox>
      <xmin>904.1859072</xmin>
      <ymin>684.186048</ymin>
      <xmax>1032.5580288</xmax>
      <ymax>963.2558879999999</ymax>
    </bndbox>
  </object>
  <object>
    <name>Pitch</name>
    <pose>Unspecified</pose>
    <truncated>0</truncated>
    <difficult>0</difficult>
    <bndbox>
      <xmin>725.581344</xmin>
      <ymin>386.51169600000003</ymin>
      <xmax>1226.046432</xmax>
      <ymax>937.209312</ymax>
    </bndbox>
  </object>
</annotation>