<annotation verified="yes">
  <folder>Annotation</folder>
  <filename>v_g053_027224.jpg</filename>
  <path>PitchAndUmpireTesting-PascalVOC-export/Annotations/v_g053_027224.jpg</path>
  <source>
    <database>Unknown</database>
  </source>
  <size>
    <width>1920</width>
    <height>1080</height>
    <depth>3</depth>
  </size>
  <segmented>0</segmented>
  <object>
    <name>Umpire</name>
    <pose>Unspecified</pose>
    <truncated>0</truncated>
    <difficult>0</difficult>
    <bndbox>
      <xmin>896.744112</xmin>
      <ymin>494.418546</ymin>
      <xmax>1008.3720480000001</xmax>
      <ymax>805.116294</ymax>
    </bndbox>
  </object>
  <object>
    <name>Pitch</name>
    <pose>Unspecified</pose>
    <truncated>0</truncated>
    <difficult>0</difficult>
    <bndbox>
      <xmin>734.883744</xmin>
      <ymin>315.81392400000004</ymin>
      <xmax>1177.674336</xmax>
      <ymax>756.744228</ymax>
    </bndbox>
  </object>
</annotation>