<annotation verified="yes">
  <folder>Annotation</folder>
  <filename>v_g045_046848.jpg</filename>
  <path>PitchAndUmpireTesting-PascalVOC-export/Annotations/v_g045_046848.jpg</path>
  <source>
    <database>Unknown</database>
  </source>
  <size>
    <width>1920</width>
    <height>1080</height>
    <depth>3</depth>
  </size>
  <segmented>0</segmented>
  <object>
    <name>Umpire</name>
    <pose>Unspecified</pose>
    <truncated>0</truncated>
    <difficult>0</difficult>
    <bndbox>
      <xmin>900.4651104000001</xmin>
      <ymin>468.3721320000001</ymin>
      <xmax>1067.9069856</xmax>
      <ymax>860.9303160000001</ymax>
    </bndbox>
  </object>
  <object>
    <name>Pitch</name>
    <pose>Unspecified</pose>
    <truncated>0</truncated>
    <difficult>0</difficult>
    <bndbox>
      <xmin>729.302304</xmin>
      <ymin>388.372158</ymin>
      <xmax>1246.511712</xmax>
      <ymax>786.511674</ymax>
    </bndbox>
  </object>
</annotation>