<annotation verified="yes">
  <folder>Annotation</folder>
  <filename>v_g036_011034.jpg</filename>
  <path>PitchAndUmpireTesting-PascalVOC-export/Annotations/v_g036_011034.jpg</path>
  <source>
    <database>Unknown</database>
  </source>
  <size>
    <width>1920</width>
    <height>1080</height>
    <depth>3</depth>
  </size>
  <segmented>0</segmented>
  <object>
    <name>Umpire</name>
    <pose>Unspecified</pose>
    <truncated>0</truncated>
    <difficult>0</difficult>
    <bndbox>
      <xmin>891.1628831999999</xmin>
      <ymin>449.76751199999995</ymin>
      <xmax>1056.7443168</xmax>
      <ymax>833.023224</ymax>
    </bndbox>
  </object>
  <object>
    <name>Pitch</name>
    <pose>Unspecified</pose>
    <truncated>0</truncated>
    <difficult>0</difficult>
    <bndbox>
      <xmin>690.232704</xmin>
      <ymin>315.813924</ymin>
      <xmax>1265.1164159999998</xmax>
      <ymax>816.279012</ymax>
    </bndbox>
  </object>
</annotation>