<annotation verified="yes">
  <folder>Annotation</folder>
  <filename>v_g091_049059.jpg</filename>
  <path>PitchAndUmpireTesting-PascalVOC-export/Annotations/v_g091_049059.jpg</path>
  <source>
    <database>Unknown</database>
  </source>
  <size>
    <width>1920</width>
    <height>1080</height>
    <depth>3</depth>
  </size>
  <segmented>0</segmented>
  <object>
    <name>Umpire</name>
    <pose>Unspecified</pose>
    <truncated>0</truncated>
    <difficult>0</difficult>
    <bndbox>
      <xmin>840.6989951999999</xmin>
      <ymin>445.864068</ymin>
      <xmax>1014.0582528</xmax>
      <ymax>887.6505960000001</ymax>
    </bndbox>
  </object>
  <object>
    <name>Pitch</name>
    <pose>Unspecified</pose>
    <truncated>0</truncated>
    <difficult>0</difficult>
    <bndbox>
      <xmin>611.4175680000001</xmin>
      <ymin>319.1068439999999</ymin>
      <xmax>1230.29136</xmax>
      <ymax>813.0873959999999</ymax>
    </bndbox>
  </object>
</annotation>