<annotation verified="yes">
  <folder>Annotation</folder>
  <filename>v_g028_012873.jpg</filename>
  <path>PitchAndUmpireTesting-PascalVOC-export/Annotations/v_g028_012873.jpg</path>
  <source>
    <database>Unknown</database>
  </source>
  <size>
    <width>1920</width>
    <height>1080</height>
    <depth>3</depth>
  </size>
  <segmented>0</segmented>
  <object>
    <name>Umpire</name>
    <pose>Unspecified</pose>
    <truncated>0</truncated>
    <difficult>0</difficult>
    <bndbox>
      <xmin>932.0930015999999</xmin>
      <ymin>591.1628400000001</ymin>
      <xmax>1066.0463903999998</xmax>
      <ymax>916.744176</ymax>
    </bndbox>
  </object>
  <object>
    <name>Pitch</name>
    <pose>Unspecified</pose>
    <truncated>0</truncated>
    <difficult>0</difficult>
    <bndbox>
      <xmin>777.6744960000001</xmin>
      <ymin>392.093028</ymin>
      <xmax>1198.13952</xmax>
      <ymax>808.837164</ymax>
    </bndbox>
  </object>
</annotation>