<annotation verified="yes">
  <folder>Annotation</folder>
  <filename>v_g046_005236.jpg</filename>
  <path>PitchAndUmpireTesting-PascalVOC-export/Annotations/v_g046_005236.jpg</path>
  <source>
    <database>Unknown</database>
  </source>
  <size>
    <width>1920</width>
    <height>1080</height>
    <depth>3</depth>
  </size>
  <segmented>0</segmented>
  <object>
    <name>Umpire</name>
    <pose>Unspecified</pose>
    <truncated>0</truncated>
    <difficult>0</difficult>
    <bndbox>
      <xmin>913.488432</xmin>
      <ymin>522.3255839999999</ymin>
      <xmax>1026.976848</xmax>
      <ymax>792.092952</ymax>
    </bndbox>
  </object>
  <object>
    <name>Pitch</name>
    <pose>Unspecified</pose>
    <truncated>0</truncated>
    <difficult>0</difficult>
    <bndbox>
      <xmin>764.6510400000001</xmin>
      <ymin>269.302374</ymin>
      <xmax>1168.371936</xmax>
      <ymax>730.697706</ymax>
    </bndbox>
  </object>
</annotation>