<annotation verified="yes">
  <folder>Annotation</folder>
  <filename>v_g037_030801.jpg</filename>
  <path>PitchAndUmpireTesting-PascalVOC-export/Annotations/v_g037_030801.jpg</path>
  <source>
    <database>Unknown</database>
  </source>
  <size>
    <width>1920</width>
    <height>1080</height>
    <depth>3</depth>
  </size>
  <segmented>0</segmented>
  <object>
    <name>Umpire</name>
    <pose>Unspecified</pose>
    <truncated>0</truncated>
    <difficult>0</difficult>
    <bndbox>
      <xmin>829.7673984</xmin>
      <ymin>494.418546</ymin>
      <xmax>991.6279296</xmax>
      <ymax>920.4650459999999</ymax>
    </bndbox>
  </object>
  <object>
    <name>Pitch</name>
    <pose>Unspecified</pose>
    <truncated>0</truncated>
    <difficult>0</difficult>
    <bndbox>
      <xmin>597.20928</xmin>
      <ymin>351.16281000000004</ymin>
      <xmax>1222.325568</xmax>
      <ymax>872.092926</ymax>
    </bndbox>
  </object>
</annotation>