<annotation verified="yes">
  <folder>Annotation</folder>
  <filename>v_g061_030790.jpg</filename>
  <path>PitchAndUmpireTesting-PascalVOC-export/Annotations/v_g061_030790.jpg</path>
  <source>
    <database>Unknown</database>
  </source>
  <size>
    <width>1920</width>
    <height>1080</height>
    <depth>3</depth>
  </size>
  <segmented>0</segmented>
  <object>
    <name>Umpire</name>
    <pose>Unspecified</pose>
    <truncated>0</truncated>
    <difficult>0</difficult>
    <bndbox>
      <xmin>896.7443136</xmin>
      <ymin>548.372106</ymin>
      <xmax>1010.2327104</xmax>
      <ymax>764.1860220000001</ymax>
    </bndbox>
  </object>
  <object>
    <name>Pitch</name>
    <pose>Unspecified</pose>
    <truncated>0</truncated>
    <difficult>0</difficult>
    <bndbox>
      <xmin>803.720928</xmin>
      <ymin>364.18609799999996</ymin>
      <xmax>1099.534752</xmax>
      <ymax>741.8604780000001</ymax>
    </bndbox>
  </object>
</annotation>