<annotation verified="yes">
  <folder>Annotation</folder>
  <filename>v_g022_025891.jpg</filename>
  <path>PitchAndUmpireTesting-PascalVOC-export/Annotations/v_g022_025891.jpg</path>
  <source>
    <database>Unknown</database>
  </source>
  <size>
    <width>1920</width>
    <height>1080</height>
    <depth>3</depth>
  </size>
  <segmented>0</segmented>
  <object>
    <name>Umpire</name>
    <pose>Unspecified</pose>
    <truncated>0</truncated>
    <difficult>0</difficult>
    <bndbox>
      <xmin>894.8836128</xmin>
      <ymin>434.88376200000005</ymin>
      <xmax>1002.7906272</xmax>
      <ymax>712.093086</ymax>
    </bndbox>
  </object>
  <object>
    <name>Pitch</name>
    <pose>Unspecified</pose>
    <truncated>0</truncated>
    <difficult>0</difficult>
    <bndbox>
      <xmin>760.9301760000001</xmin>
      <ymin>375.34881599999994</ymin>
      <xmax>1153.488384</xmax>
      <ymax>663.720912</ymax>
    </bndbox>
  </object>
</annotation>