<annotation verified="yes">
  <folder>Annotation</folder>
  <filename>v_g022_006520.jpg</filename>
  <path>PitchAndUmpireTesting-PascalVOC-export/Annotations/v_g022_006520.jpg</path>
  <source>
    <database>Unknown</database>
  </source>
  <size>
    <width>1920</width>
    <height>1080</height>
    <depth>3</depth>
  </size>
  <segmented>0</segmented>
  <object>
    <name>Umpire</name>
    <pose>Unspecified</pose>
    <truncated>0</truncated>
    <difficult>0</difficult>
    <bndbox>
      <xmin>893.0232672</xmin>
      <ymin>607.9069979999999</ymin>
      <xmax>1032.5581728</xmax>
      <ymax>942.790698</ymax>
    </bndbox>
  </object>
  <object>
    <name>Pitch</name>
    <pose>Unspecified</pose>
    <truncated>0</truncated>
    <difficult>0</difficult>
    <bndbox>
      <xmin>749.767488</xmin>
      <ymin>410.69770200000005</ymin>
      <xmax>1170.232512</xmax>
      <ymax>853.4883060000001</ymax>
    </bndbox>
  </object>
</annotation>