<annotation verified="yes">
    <folder>Annotation</folder>
    <filename>v_g007_c017_32410.jpg</filename>
    <path>Test-Balls-PascalVOC-export/Annotations/v_g007_c017_32410.jpg</path>
    <source>
        <database>Unknown</database>
    </source>
    <size>
        <width>768</width>
        <height>594</height>
        <depth>3</depth>
    </size>
    <segmented>0</segmented>
    <object>
    <name>Ball</name>
    <pose>Unspecified</pose>
    <truncated>0</truncated>
    <difficult>0</difficult>
    <bndbox>
        <xmin>269.08217446270544</xmin>
        <ymin>251.38235294117646</ymin>
        <xmax>301.12262958280655</xmax>
        <ymax>278.55882352941177</ymax>
    </bndbox>
</object>
</annotation>
