<annotation verified="yes">
    <folder>Annotation</folder>
    <filename>v_g005_c120_250618.jpg</filename>
    <path>Test-Balls-PascalVOC-export/Annotations/v_g005_c120_250618.jpg</path>
    <source>
        <database>Unknown</database>
    </source>
    <size>
        <width>512</width>
        <height>396</height>
        <depth>3</depth>
    </size>
    <segmented>0</segmented>
    <object>
    <name>Ball</name>
    <pose>Unspecified</pose>
    <truncated>0</truncated>
    <difficult>0</difficult>
    <bndbox>
        <xmin>197.51201011378004</xmin>
        <ymin>278.88235294117646</ymin>
        <xmax>218.2250316055626</xmax>
        <ymax>296.3529411764706</ymax>
    </bndbox>
</object>
</annotation>
