<annotation verified="yes">
    <folder>Annotation</folder>
    <filename>v_g005_c069_208866.jpg</filename>
    <path>Test-Balls-PascalVOC-export/Annotations/v_g005_c069_208866.jpg</path>
    <source>
        <database>Unknown</database>
    </source>
    <size>
        <width>512</width>
        <height>396</height>
        <depth>3</depth>
    </size>
    <segmented>0</segmented>
    <object>
    <name>Ball</name>
    <pose>Unspecified</pose>
    <truncated>0</truncated>
    <difficult>0</difficult>
    <bndbox>
        <xmin>211.42857142857144</xmin>
        <ymin>223.23529411764707</ymin>
        <xmax>230.84702907711758</xmax>
        <ymax>240.7058823529412</ymax>
    </bndbox>
</object>
</annotation>
