<annotation verified="yes">
    <folder>Annotation</folder>
    <filename>v_g007_c048_78889.jpg</filename>
    <path>Test-Balls-PascalVOC-export/Annotations/v_g007_c048_78889.jpg</path>
    <source>
        <database>Unknown</database>
    </source>
    <size>
        <width>768</width>
        <height>594</height>
        <depth>3</depth>
    </size>
    <segmented>0</segmented>
    <object>
    <name>Ball</name>
    <pose>Unspecified</pose>
    <truncated>0</truncated>
    <difficult>0</difficult>
    <bndbox>
        <xmin>242.86725663716814</xmin>
        <ymin>534.7941176470588</ymin>
        <xmax>275.8786346396966</xmax>
        <ymax>556.1470588235294</ymax>
    </bndbox>
</object>
</annotation>
