<annotation verified="yes">
    <folder>Annotation</folder>
    <filename>v_g005_c118_241294.jpg</filename>
    <path>Test-Balls-PascalVOC-export/Annotations/v_g005_c118_241294.jpg</path>
    <source>
        <database>Unknown</database>
    </source>
    <size>
        <width>512</width>
        <height>396</height>
        <depth>3</depth>
    </size>
    <segmented>0</segmented>
    <object>
    <name>Ball</name>
    <pose>Unspecified</pose>
    <truncated>0</truncated>
    <difficult>0</difficult>
    <bndbox>
        <xmin>169.67888748419722</xmin>
        <ymin>280.1764705882353</ymin>
        <xmax>198.80657395701644</xmax>
        <ymax>297.64705882352945</ymax>
    </bndbox>
</object>
</annotation>
