<annotation verified="yes">
    <folder>Annotation</folder>
    <filename>v_g007_c184_283320.jpg</filename>
    <path>Test-Balls-PascalVOC-export/Annotations/v_g007_c184_283320.jpg</path>
    <source>
        <database>Unknown</database>
    </source>
    <size>
        <width>768</width>
        <height>594</height>
        <depth>3</depth>
    </size>
    <segmented>0</segmented>
    <object>
    <name>Ball</name>
    <pose>Unspecified</pose>
    <truncated>0</truncated>
    <difficult>0</difficult>
    <bndbox>
        <xmin>451.6156763590392</xmin>
        <ymin>240.7058823529412</ymin>
        <xmax>481.7142857142857</xmax>
        <ymax>266.9117647058824</ymax>
    </bndbox>
</object>
</annotation>
