<annotation verified="yes">
    <folder>Annotation</folder>
    <filename>v_g007_c063_90258.jpg</filename>
    <path>Test-Balls-PascalVOC-export/Annotations/v_g007_c063_90258.jpg</path>
    <source>
        <database>Unknown</database>
    </source>
    <size>
        <width>768</width>
        <height>594</height>
        <depth>3</depth>
    </size>
    <segmented>0</segmented>
    <object>
    <name>Ball</name>
    <pose>Unspecified</pose>
    <truncated>0</truncated>
    <difficult>0</difficult>
    <bndbox>
        <xmin>256.46017699115043</xmin>
        <ymin>527.0294117647059</ymin>
        <xmax>301.12262958280655</xmax>
        <ymax>551.2941176470588</ymax>
    </bndbox>
</object>
</annotation>
