<annotation verified="yes">
    <folder>Annotation</folder>
    <filename>v_g005_c099_203286.jpg</filename>
    <path>Test-Balls-PascalVOC-export/Annotations/v_g005_c099_203286.jpg</path>
    <source>
        <database>Unknown</database>
    </source>
    <size>
        <width>512</width>
        <height>396</height>
        <depth>3</depth>
    </size>
    <segmented>0</segmented>
    <object>
    <name>Ball</name>
    <pose>Unspecified</pose>
    <truncated>0</truncated>
    <difficult>0</difficult>
    <bndbox>
        <xmin>223.07964601769913</xmin>
        <ymin>300.2352941176471</ymin>
        <xmax>248.32364096080912</xmax>
        <ymax>317.05882352941177</ymax>
    </bndbox>
</object>
</annotation>
