<annotation verified="yes">
    <folder>Annotation</folder>
    <filename>v_g007_c098_145600.jpg</filename>
    <path>Test-Balls-PascalVOC-export/Annotations/v_g007_c098_145600.jpg</path>
    <source>
        <database>Unknown</database>
    </source>
    <size>
        <width>768</width>
        <height>594</height>
        <depth>3</depth>
    </size>
    <segmented>0</segmented>
    <object>
    <name>Ball</name>
    <pose>Unspecified</pose>
    <truncated>0</truncated>
    <difficult>0</difficult>
    <bndbox>
        <xmin>349.1833122629583</xmin>
        <ymin>427.05882352941177</ymin>
        <xmax>375.39823008849555</xmax>
        <ymax>447.44117647058823</ymax>
    </bndbox>
</object>
</annotation>
