<annotation verified="yes">
    <folder>Annotation</folder>
    <filename>v_g007_c111_167293.jpg</filename>
    <path>Test-Balls-PascalVOC-export/Annotations/v_g007_c111_167293.jpg</path>
    <source>
        <database>Unknown</database>
    </source>
    <size>
        <width>768</width>
        <height>594</height>
        <depth>3</depth>
    </size>
    <segmented>0</segmented>
    <object>
    <name>Ball</name>
    <pose>Unspecified</pose>
    <truncated>0</truncated>
    <difficult>0</difficult>
    <bndbox>
        <xmin>276.84955752212386</xmin>
        <ymin>515.3823529411765</ymin>
        <xmax>330.2503160556258</xmax>
        <ymax>551.2941176470588</ymax>
    </bndbox>
</object>
</annotation>
