<annotation verified="yes">
    <folder>Annotation</folder>
    <filename>v_g005_c024_42058.jpg</filename>
    <path>Test-Balls-PascalVOC-export/Annotations/v_g005_c024_42058.jpg</path>
    <source>
        <database>Unknown</database>
    </source>
    <size>
        <width>512</width>
        <height>396</height>
        <depth>3</depth>
    </size>
    <segmented>0</segmented>
    <object>
    <name>Ball</name>
    <pose>Unspecified</pose>
    <truncated>0</truncated>
    <difficult>0</difficult>
    <bndbox>
        <xmin>151.55499367888748</xmin>
        <ymin>164.3529411764706</ymin>
        <xmax>172.91529709228826</xmax>
        <ymax>181.82352941176472</ymax>
    </bndbox>
</object>
</annotation>
